{"box_data": [{"position": {"minX": 18.5, "minY": -43.5, "maxX": 650.0, "maxY": 640.5}, "class_id": 0, "box_caption": "balloons 0.778", "scores": {"class_score": 0.77783203125}, "domain": "pixel"}, {"position": {"minX": -5.75, "minY": -81.5, "maxX": 677.0, "maxY": 370.0}, "class_id": 0, "box_caption": "balloons 0.082", "scores": {"class_score": 0.082275390625}, "domain": "pixel"}, {"position": {"minX": -42.625, "minY": 13.25, "maxX": 219.625, "maxY": 665.0}, "class_id": 0, "box_caption": "balloons 0.061", "scores": {"class_score": 0.06085205078125}, "domain": "pixel"}, {"position": {"minX": -25.25, "minY": 193.75, "maxX": 702.0, "maxY": 667.0}, "class_id": 0, "box_caption": "balloons 0.022", "scores": {"class_score": 0.0215301513671875}, "domain": "pixel"}, {"position": {"minX": -13.375, "minY": 14.0, "maxX": 373.5, "maxY": 668.0}, "class_id": 0, "box_caption": "balloons 0.020", "scores": {"class_score": 0.0204925537109375}, "domain": "pixel"}, {"position": {"minX": 45.5, "minY": -72.0, "maxX": 630.0, "maxY": 151.375}, "class_id": 0, "box_caption": "balloons 0.017", "scores": {"class_score": 0.01678466796875}, "domain": "pixel"}, {"position": {"minX": -45.5, "minY": 40.5, "maxX": 93.875, "maxY": 649.5}, "class_id": 0, "box_caption": "balloons 0.009", "scores": {"class_score": 0.009124755859375}, "domain": "pixel"}, {"position": {"minX": -35.5625, "minY": -85.375, "maxX": 126.8125, "maxY": 134.875}, "class_id": 0, "box_caption": "balloons 0.008", "scores": {"class_score": 0.007965087890625}, "domain": "pixel"}, {"position": {"minX": 21.375, "minY": 18.0, "maxX": 282.5, "maxY": 263.75}, "class_id": 0, "box_caption": "balloons 0.008", "scores": {"class_score": 0.007785797119140625}, "domain": "pixel"}, {"position": {"minX": -49.5625, "minY": 531.5, "maxX": 89.9375, "maxY": 733.5}, "class_id": 0, "box_caption": "balloons 0.008", "scores": {"class_score": 0.007785797119140625}, "domain": "pixel"}, {"position": {"minX": 484.5, "minY": 34.25, "maxX": 705.5, "maxY": 580.0}, "class_id": 0, "box_caption": "balloons 0.007", "scores": {"class_score": 0.006771087646484375}, "domain": "pixel"}, {"position": {"minX": -33.1875, "minY": -54.125, "maxX": 185.0, "maxY": 104.125}, "class_id": 0, "box_caption": "balloons 0.007", "scores": {"class_score": 0.0066680908203125}, "domain": "pixel"}, {"position": {"minX": -75.6875, "minY": 569.0, "maxX": 113.1875, "maxY": 756.0}, "class_id": 0, "box_caption": "balloons 0.007", "scores": {"class_score": 0.006587982177734375}, "domain": "pixel"}, {"position": {"minX": -43.0, "minY": -30.6875, "maxX": 585.5, "maxY": 181.25}, "class_id": 0, "box_caption": "balloons 0.007", "scores": {"class_score": 0.006565093994140625}, "domain": "pixel"}, {"position": {"minX": 226.0, "minY": -16.9375, "maxX": 632.5, "maxY": 158.5}, "class_id": 0, "box_caption": "balloons 0.007", "scores": {"class_score": 0.00653839111328125}, "domain": "pixel"}, {"position": {"minX": 527.5, "minY": -41.28125, "maxX": 662.5, "maxY": 153.25}, "class_id": 0, "box_caption": "balloons 0.006", "scores": {"class_score": 0.006488800048828125}, "domain": "pixel"}, {"position": {"minX": 18.25, "minY": 36.5625, "maxX": 293.25, "maxY": 187.25}, "class_id": 0, "box_caption": "balloons 0.006", "scores": {"class_score": 0.006439208984375}, "domain": "pixel"}, {"position": {"minX": 346.75, "minY": 567.5, "maxX": 703.0, "maxY": 765.5}, "class_id": 0, "box_caption": "balloons 0.006", "scores": {"class_score": 0.006439208984375}, "domain": "pixel"}, {"position": {"minX": 537.5, "minY": 534.5, "maxX": 692.5, "maxY": 787.5}, "class_id": 0, "box_caption": "balloons 0.006", "scores": {"class_score": 0.006389617919921875}, "domain": "pixel"}, {"position": {"minX": -30.40625, "minY": 212.5, "maxX": 78.5, "maxY": 666.0}, "class_id": 0, "box_caption": "balloons 0.006", "scores": {"class_score": 0.00609588623046875}, "domain": "pixel"}, {"position": {"minX": 245.25, "minY": 33.96875, "maxX": 619.0, "maxY": 115.625}, "class_id": 0, "box_caption": "balloons 0.006", "scores": {"class_score": 0.006072998046875}, "domain": "pixel"}, {"position": {"minX": 449.25, "minY": -2.0625, "maxX": 670.0, "maxY": 220.5}, "class_id": 0, "box_caption": "balloons 0.006", "scores": {"class_score": 0.00595855712890625}, "domain": "pixel"}, {"position": {"minX": -105.625, "minY": 465.25, "maxX": 148.125, "maxY": 768.0}, "class_id": 0, "box_caption": "balloons 0.006", "scores": {"class_score": 0.00595855712890625}, "domain": "pixel"}, {"position": {"minX": 65.5, "minY": 422.5, "maxX": 592.0, "maxY": 759.5}, "class_id": 0, "box_caption": "balloons 0.006", "scores": {"class_score": 0.00577545166015625}, "domain": "pixel"}, {"position": {"minX": 556.5, "minY": -43.8125, "maxX": 675.5, "maxY": 198.75}, "class_id": 0, "box_caption": "balloons 0.006", "scores": {"class_score": 0.0057525634765625}, "domain": "pixel"}, {"position": {"minX": 509.75, "minY": -40.375, "maxX": 678.0, "maxY": 262.0}, "class_id": 0, "box_caption": "balloons 0.006", "scores": {"class_score": 0.0057525634765625}, "domain": "pixel"}, {"position": {"minX": -10.875, "minY": -15.25, "maxX": 359.0, "maxY": 292.25}, "class_id": 0, "box_caption": "balloons 0.006", "scores": {"class_score": 0.00572967529296875}, "domain": "pixel"}, {"position": {"minX": 508.25, "minY": 396.0, "maxX": 650.5, "maxY": 698.0}, "class_id": 0, "box_caption": "balloons 0.006", "scores": {"class_score": 0.005641937255859375}, "domain": "pixel"}, {"position": {"minX": 71.75, "minY": 19.125, "maxX": 673.0, "maxY": 472.0}, "class_id": 0, "box_caption": "balloons 0.006", "scores": {"class_score": 0.005619049072265625}, "domain": "pixel"}, {"position": {"minX": 327.5, "minY": 461.5, "maxX": 559.5, "maxY": 668.5}, "class_id": 0, "box_caption": "balloons 0.006", "scores": {"class_score": 0.0055999755859375}, "domain": "pixel"}, {"position": {"minX": 153.125, "minY": -43.25, "maxX": 652.0, "maxY": 197.0}, "class_id": 0, "box_caption": "balloons 0.006", "scores": {"class_score": 0.0055999755859375}, "domain": "pixel"}, {"position": {"minX": 306.5, "minY": 33.625, "maxX": 617.0, "maxY": 175.375}, "class_id": 0, "box_caption": "balloons 0.006", "scores": {"class_score": 0.005512237548828125}, "domain": "pixel"}, {"position": {"minX": 571.0, "minY": 309.5, "maxX": 745.0, "maxY": 688.5}, "class_id": 0, "box_caption": "balloons 0.005", "scores": {"class_score": 0.005344390869140625}, "domain": "pixel"}, {"position": {"minX": 73.875, "minY": 516.5, "maxX": 485.0, "maxY": 780.5}, "class_id": 0, "box_caption": "balloons 0.005", "scores": {"class_score": 0.005199432373046875}, "domain": "pixel"}, {"position": {"minX": -10.125, "minY": -32.0625, "maxX": 314.0, "maxY": 198.75}, "class_id": 0, "box_caption": "balloons 0.005", "scores": {"class_score": 0.00511932373046875}, "domain": "pixel"}, {"position": {"minX": 196.375, "minY": 501.5, "maxX": 547.5, "maxY": 762.5}, "class_id": 0, "box_caption": "balloons 0.005", "scores": {"class_score": 0.00511932373046875}, "domain": "pixel"}, {"position": {"minX": 553.5, "minY": 574.5, "maxX": 701.5, "maxY": 679.5}, "class_id": 0, "box_caption": "balloons 0.005", "scores": {"class_score": 0.005100250244140625}, "domain": "pixel"}, {"position": {"minX": 381.5, "minY": 49.25, "maxX": 685.5, "maxY": 629.0}, "class_id": 0, "box_caption": "balloons 0.005", "scores": {"class_score": 0.00498199462890625}, "domain": "pixel"}, {"position": {"minX": -42.6875, "minY": 476.5, "maxX": 68.375, "maxY": 658.5}, "class_id": 0, "box_caption": "balloons 0.005", "scores": {"class_score": 0.004962921142578125}, "domain": "pixel"}, {"position": {"minX": 425.5, "minY": -85.125, "maxX": 698.5, "maxY": 295.5}, "class_id": 0, "box_caption": "balloons 0.005", "scores": {"class_score": 0.0048675537109375}, "domain": "pixel"}, {"position": {"minX": -22.9375, "minY": 544.0, "maxX": 267.25, "maxY": 697.0}, "class_id": 0, "box_caption": "balloons 0.005", "scores": {"class_score": 0.00482940673828125}, "domain": "pixel"}, {"position": {"minX": 263.75, "minY": 483.5, "maxX": 670.0, "maxY": 757.5}, "class_id": 0, "box_caption": "balloons 0.005", "scores": {"class_score": 0.004791259765625}, "domain": "pixel"}, {"position": {"minX": -57.75, "minY": -90.0625, "maxX": 280.75, "maxY": 163.25}, "class_id": 0, "box_caption": "balloons 0.005", "scores": {"class_score": 0.004680633544921875}, "domain": "pixel"}, {"position": {"minX": 22.625, "minY": -0.6875, "maxX": 492.0, "maxY": 129.5}, "class_id": 0, "box_caption": "balloons 0.005", "scores": {"class_score": 0.00453948974609375}, "domain": "pixel"}, {"position": {"minX": 519.0, "minY": 4.75, "maxX": 684.0, "maxY": 100.8125}, "class_id": 0, "box_caption": "balloons 0.004", "scores": {"class_score": 0.004486083984375}, "domain": "pixel"}, {"position": {"minX": -79.4375, "minY": 362.5, "maxX": 121.6875, "maxY": 736.5}, "class_id": 0, "box_caption": "balloons 0.004", "scores": {"class_score": 0.004451751708984375}, "domain": "pixel"}, {"position": {"minX": 462.0, "minY": -27.53125, "maxX": 659.0, "maxY": 132.25}, "class_id": 0, "box_caption": "balloons 0.004", "scores": {"class_score": 0.004398345947265625}, "domain": "pixel"}, {"position": {"minX": 535.5, "minY": 457.75, "maxX": 657.5, "maxY": 682.0}, "class_id": 0, "box_caption": "balloons 0.004", "scores": {"class_score": 0.0043487548828125}, "domain": "pixel"}, {"position": {"minX": 632.5, "minY": 294.25, "maxX": 701.5, "maxY": 552.0}, "class_id": 0, "box_caption": "balloons 0.004", "scores": {"class_score": 0.00426483154296875}, "domain": "pixel"}, {"position": {"minX": 196.0, "minY": 176.25, "maxX": 480.5, "maxY": 430.25}, "class_id": 0, "box_caption": "balloons 0.004", "scores": {"class_score": 0.004199981689453125}, "domain": "pixel"}, {"position": {"minX": -19.40625, "minY": 481.5, "maxX": 70.375, "maxY": 583.5}, "class_id": 0, "box_caption": "balloons 0.004", "scores": {"class_score": 0.004180908203125}, "domain": "pixel"}, {"position": {"minX": 189.375, "minY": 562.0, "maxX": 595.5, "maxY": 716.0}, "class_id": 0, "box_caption": "balloons 0.004", "scores": {"class_score": 0.004180908203125}, "domain": "pixel"}, {"position": {"minX": 497.75, "minY": -63.34375, "maxX": 694.0, "maxY": 144.25}, "class_id": 0, "box_caption": "balloons 0.004", "scores": {"class_score": 0.0041656494140625}, "domain": "pixel"}, {"position": {"minX": 520.0, "minY": 353.75, "maxX": 679.0, "maxY": 766.0}, "class_id": 0, "box_caption": "balloons 0.004", "scores": {"class_score": 0.0041656494140625}, "domain": "pixel"}, {"position": {"minX": 34.5, "minY": -27.5625, "maxX": 556.0, "maxY": 104.4375}, "class_id": 0, "box_caption": "balloons 0.004", "scores": {"class_score": 0.0041351318359375}, "domain": "pixel"}, {"position": {"minX": 55.625, "minY": -8.125, "maxX": 553.0, "maxY": 344.0}, "class_id": 0, "box_caption": "balloons 0.004", "scores": {"class_score": 0.004100799560546875}, "domain": "pixel"}, {"position": {"minX": 179.125, "minY": 231.125, "maxX": 499.5, "maxY": 488.5}, "class_id": 0, "box_caption": "balloons 0.004", "scores": {"class_score": 0.004070281982421875}, "domain": "pixel"}, {"position": {"minX": 488.75, "minY": 537.5, "maxX": 671.5, "maxY": 725.5}, "class_id": 0, "box_caption": "balloons 0.004", "scores": {"class_score": 0.004055023193359375}, "domain": "pixel"}, {"position": {"minX": 559.0, "minY": 2.0, "maxX": 692.0, "maxY": 151.375}, "class_id": 0, "box_caption": "balloons 0.004", "scores": {"class_score": 0.00400543212890625}, "domain": "pixel"}, {"position": {"minX": -76.375, "minY": 490.0, "maxX": 157.875, "maxY": 699.0}, "class_id": 0, "box_caption": "balloons 0.004", "scores": {"class_score": 0.00400543212890625}, "domain": "pixel"}, {"position": {"minX": -53.65625, "minY": -40.875, "maxX": 155.25, "maxY": 65.5}, "class_id": 0, "box_caption": "balloons 0.004", "scores": {"class_score": 0.00399017333984375}, "domain": "pixel"}, {"position": {"minX": 317.75, "minY": 516.5, "maxX": 548.5, "maxY": 732.5}, "class_id": 0, "box_caption": "balloons 0.004", "scores": {"class_score": 0.00395965576171875}, "domain": "pixel"}, {"position": {"minX": 268.0, "minY": 428.25, "maxX": 599.0, "maxY": 680.5}, "class_id": 0, "box_caption": "balloons 0.004", "scores": {"class_score": 0.0038394927978515625}, "domain": "pixel"}, {"position": {"minX": -77.8125, "minY": -155.875, "maxX": 115.4375, "maxY": 172.625}, "class_id": 0, "box_caption": "balloons 0.004", "scores": {"class_score": 0.0037364959716796875}, "domain": "pixel"}, {"position": {"minX": 40.4375, "minY": 409.25, "maxX": 240.75, "maxY": 650.0}, "class_id": 0, "box_caption": "balloons 0.004", "scores": {"class_score": 0.0037078857421875}, "domain": "pixel"}, {"position": {"minX": 597.0, "minY": 255.0, "maxX": 711.0, "maxY": 729.0}, "class_id": 0, "box_caption": "balloons 0.004", "scores": {"class_score": 0.003650665283203125}, "domain": "pixel"}, {"position": {"minX": -52.625, "minY": 394.5, "maxX": 286.0, "maxY": 716.5}, "class_id": 0, "box_caption": "balloons 0.004", "scores": {"class_score": 0.003635406494140625}, "domain": "pixel"}, {"position": {"minX": 189.75, "minY": 40.5, "maxX": 492.75, "maxY": 297.25}, "class_id": 0, "box_caption": "balloons 0.004", "scores": {"class_score": 0.0036067962646484375}, "domain": "pixel"}, {"position": {"minX": -42.1875, "minY": 188.0, "maxX": 140.5, "maxY": 680.0}, "class_id": 0, "box_caption": "balloons 0.004", "scores": {"class_score": 0.0036067962646484375}, "domain": "pixel"}, {"position": {"minX": 289.5, "minY": -59.5625, "maxX": 642.5, "maxY": 272.25}, "class_id": 0, "box_caption": "balloons 0.004", "scores": {"class_score": 0.0036067962646484375}, "domain": "pixel"}, {"position": {"minX": 568.5, "minY": 610.0, "maxX": 692.5, "maxY": 696.0}, "class_id": 0, "box_caption": "balloons 0.004", "scores": {"class_score": 0.0035800933837890625}, "domain": "pixel"}, {"position": {"minX": 85.1875, "minY": 38.0, "maxX": 337.25, "maxY": 306.25}, "class_id": 0, "box_caption": "balloons 0.004", "scores": {"class_score": 0.0035247802734375}, "domain": "pixel"}, {"position": {"minX": -18.5625, "minY": -37.59375, "maxX": 235.75, "maxY": 75.125}, "class_id": 0, "box_caption": "balloons 0.003", "scores": {"class_score": 0.0034694671630859375}, "domain": "pixel"}, {"position": {"minX": 238.875, "minY": 1.75, "maxX": 615.5, "maxY": 693.0}, "class_id": 0, "box_caption": "balloons 0.003", "scores": {"class_score": 0.00345611572265625}, "domain": "pixel"}, {"position": {"minX": 624.0, "minY": 340.0, "maxX": 707.0, "maxY": 607.5}, "class_id": 0, "box_caption": "balloons 0.003", "scores": {"class_score": 0.003376007080078125}, "domain": "pixel"}, {"position": {"minX": -59.5, "minY": 558.5, "maxX": 153.375, "maxY": 690.5}, "class_id": 0, "box_caption": "balloons 0.003", "scores": {"class_score": 0.0033512115478515625}, "domain": "pixel"}, {"position": {"minX": 391.75, "minY": -60.875, "maxX": 677.0, "maxY": 143.375}, "class_id": 0, "box_caption": "balloons 0.003", "scores": {"class_score": 0.0033512115478515625}, "domain": "pixel"}, {"position": {"minX": 421.75, "minY": 481.5, "maxX": 582.5, "maxY": 695.5}, "class_id": 0, "box_caption": "balloons 0.003", "scores": {"class_score": 0.003337860107421875}, "domain": "pixel"}, {"position": {"minX": 570.0, "minY": 13.1875, "maxX": 678.0, "maxY": 263.75}, "class_id": 0, "box_caption": "balloons 0.003", "scores": {"class_score": 0.0033245086669921875}, "domain": "pixel"}, {"position": {"minX": 380.0, "minY": -35.125, "maxX": 672.0, "maxY": 247.375}, "class_id": 0, "box_caption": "balloons 0.003", "scores": {"class_score": 0.0033245086669921875}, "domain": "pixel"}, {"position": {"minX": -60.0625, "minY": 569.0, "maxX": 87.8125, "maxY": 679.0}, "class_id": 0, "box_caption": "balloons 0.003", "scores": {"class_score": 0.0033111572265625}, "domain": "pixel"}, {"position": {"minX": 223.875, "minY": -16.75, "maxX": 644.5, "maxY": 359.75}, "class_id": 0, "box_caption": "balloons 0.003", "scores": {"class_score": 0.0033111572265625}, "domain": "pixel"}, {"position": {"minX": -42.8125, "minY": -105.3125, "maxX": 199.5, "maxY": 255.5}, "class_id": 0, "box_caption": "balloons 0.003", "scores": {"class_score": 0.0032482147216796875}, "domain": "pixel"}, {"position": {"minX": -26.53125, "minY": 397.0, "maxX": 72.25, "maxY": 681.0}, "class_id": 0, "box_caption": "balloons 0.003", "scores": {"class_score": 0.0031604766845703125}, "domain": "pixel"}, {"position": {"minX": 297.25, "minY": 187.375, "maxX": 443.75, "maxY": 369.0}, "class_id": 0, "box_caption": "balloons 0.003", "scores": {"class_score": 0.003147125244140625}, "domain": "pixel"}, {"position": {"minX": 330.25, "minY": 206.25, "maxX": 462.75, "maxY": 347.75}, "class_id": 0, "box_caption": "balloons 0.003", "scores": {"class_score": 0.003147125244140625}, "domain": "pixel"}, {"position": {"minX": 197.25, "minY": 165.75, "maxX": 354.75, "maxY": 322.25}, "class_id": 0, "box_caption": "balloons 0.003", "scores": {"class_score": 0.003124237060546875}, "domain": "pixel"}, {"position": {"minX": -72.125, "minY": 6.28125, "maxX": 122.375, "maxY": 90.625}, "class_id": 0, "box_caption": "balloons 0.003", "scores": {"class_score": 0.0031108856201171875}, "domain": "pixel"}, {"position": {"minX": 612.0, "minY": 568.5, "maxX": 708.0, "maxY": 680.5}, "class_id": 0, "box_caption": "balloons 0.003", "scores": {"class_score": 0.0030994415283203125}, "domain": "pixel"}, {"position": {"minX": 422.0, "minY": 6.375, "maxX": 651.0, "maxY": 97.0625}, "class_id": 0, "box_caption": "balloons 0.003", "scores": {"class_score": 0.0030879974365234375}, "domain": "pixel"}, {"position": {"minX": 13.875, "minY": 550.0, "maxX": 292.5, "maxY": 752.0}, "class_id": 0, "box_caption": "balloons 0.003", "scores": {"class_score": 0.0030879974365234375}, "domain": "pixel"}, {"position": {"minX": -20.0625, "minY": 284.5, "maxX": 244.25, "maxY": 704.5}, "class_id": 0, "box_caption": "balloons 0.003", "scores": {"class_score": 0.003063201904296875}, "domain": "pixel"}, {"position": {"minX": 525.0, "minY": 586.0, "maxX": 685.0, "maxY": 722.0}, "class_id": 0, "box_caption": "balloons 0.003", "scores": {"class_score": 0.0030269622802734375}, "domain": "pixel"}, {"position": {"minX": -4.8125, "minY": 413.75, "maxX": 171.25, "maxY": 704.0}, "class_id": 0, "box_caption": "balloons 0.003", "scores": {"class_score": 0.0030269622802734375}, "domain": "pixel"}, {"position": {"minX": 31.359375, "minY": 30.921875, "maxX": 94.3125, "maxY": 69.75}, "class_id": 0, "box_caption": "balloons 0.003", "scores": {"class_score": 0.0029926300048828125}, "domain": "pixel"}, {"position": {"minX": 149.5, "minY": -87.4375, "maxX": 588.5, "maxY": 113.3125}, "class_id": 0, "box_caption": "balloons 0.003", "scores": {"class_score": 0.0029354095458984375}, "domain": "pixel"}, {"position": {"minX": -33.0, "minY": 520.0, "maxX": 211.25, "maxY": 783.0}, "class_id": 0, "box_caption": "balloons 0.003", "scores": {"class_score": 0.0029354095458984375}, "domain": "pixel"}, {"position": {"minX": 424.0, "minY": 10.3125, "maxX": 645.0, "maxY": 151.0}, "class_id": 0, "box_caption": "balloons 0.003", "scores": {"class_score": 0.0029239654541015625}, "domain": "pixel"}, {"position": {"minX": 324.0, "minY": 155.25, "maxX": 467.0, "maxY": 329.0}, "class_id": 0, "box_caption": "balloons 0.003", "scores": {"class_score": 0.0029239654541015625}, "domain": "pixel"}, {"position": {"minX": 516.0, "minY": 487.0, "maxX": 638.0, "maxY": 701.0}, "class_id": 0, "box_caption": "balloons 0.003", "scores": {"class_score": 0.0029125213623046875}, "domain": "pixel"}, {"position": {"minX": -36.90625, "minY": 529.5, "maxX": 118.375, "maxY": 665.5}, "class_id": 0, "box_caption": "balloons 0.003", "scores": {"class_score": 0.00284576416015625}, "domain": "pixel"}, {"position": {"minX": 34.25, "minY": 521.5, "maxX": 387.75, "maxY": 720.5}, "class_id": 0, "box_caption": "balloons 0.003", "scores": {"class_score": 0.00284576416015625}, "domain": "pixel"}, {"position": {"minX": 306.5, "minY": 344.0, "maxX": 629.5, "maxY": 776.0}, "class_id": 0, "box_caption": "balloons 0.003", "scores": {"class_score": 0.00279998779296875}, "domain": "pixel"}, {"position": {"minX": -20.09375, "minY": -79.875, "maxX": 128.75, "maxY": 307.0}, "class_id": 0, "box_caption": "balloons 0.003", "scores": {"class_score": 0.0027790069580078125}, "domain": "pixel"}, {"position": {"minX": 30.75, "minY": 41.40625, "maxX": 323.25, "maxY": 141.375}, "class_id": 0, "box_caption": "balloons 0.003", "scores": {"class_score": 0.0027675628662109375}, "domain": "pixel"}, {"position": {"minX": 16.0, "minY": 364.5, "maxX": 204.75, "maxY": 627.0}, "class_id": 0, "box_caption": "balloons 0.003", "scores": {"class_score": 0.00274658203125}, "domain": "pixel"}, {"position": {"minX": 538.5, "minY": -26.0, "maxX": 714.5, "maxY": 375.0}, "class_id": 0, "box_caption": "balloons 0.003", "scores": {"class_score": 0.0027370452880859375}, "domain": "pixel"}, {"position": {"minX": 584.0, "minY": 602.0, "maxX": 727.0, "maxY": 707.0}, "class_id": 0, "box_caption": "balloons 0.003", "scores": {"class_score": 0.0027141571044921875}, "domain": "pixel"}, {"position": {"minX": 125.125, "minY": 30.734375, "maxX": 300.0, "maxY": 68.5}, "class_id": 0, "box_caption": "balloons 0.003", "scores": {"class_score": 0.002704620361328125}, "domain": "pixel"}, {"position": {"minX": -56.40625, "minY": -19.25, "maxX": 100.25, "maxY": 316.75}, "class_id": 0, "box_caption": "balloons 0.003", "scores": {"class_score": 0.002704620361328125}, "domain": "pixel"}, {"position": {"minX": 419.5, "minY": 511.75, "maxX": 709.5, "maxY": 796.0}, "class_id": 0, "box_caption": "balloons 0.003", "scores": {"class_score": 0.002704620361328125}, "domain": "pixel"}, {"position": {"minX": 395.0, "minY": 384.25, "maxX": 658.0, "maxY": 792.0}, "class_id": 0, "box_caption": "balloons 0.003", "scores": {"class_score": 0.00266265869140625}, "domain": "pixel"}, {"position": {"minX": 530.0, "minY": 609.5, "maxX": 649.0, "maxY": 674.5}, "class_id": 0, "box_caption": "balloons 0.003", "scores": {"class_score": 0.0026531219482421875}, "domain": "pixel"}, {"position": {"minX": 549.0, "minY": 470.5, "maxX": 760.0, "maxY": 827.5}, "class_id": 0, "box_caption": "balloons 0.003", "scores": {"class_score": 0.0026531219482421875}, "domain": "pixel"}, {"position": {"minX": 247.125, "minY": 53.5, "maxX": 559.5, "maxY": 421.5}, "class_id": 0, "box_caption": "balloons 0.003", "scores": {"class_score": 0.00263214111328125}, "domain": "pixel"}, {"position": {"minX": 223.375, "minY": 18.375, "maxX": 573.0, "maxY": 85.5}, "class_id": 0, "box_caption": "balloons 0.003", "scores": {"class_score": 0.002620697021484375}, "domain": "pixel"}, {"position": {"minX": 72.75, "minY": 52.03125, "maxX": 468.25, "maxY": 91.625}, "class_id": 0, "box_caption": "balloons 0.003", "scores": {"class_score": 0.0026111602783203125}, "domain": "pixel"}, {"position": {"minX": 124.0, "minY": 34.6875, "maxX": 504.0, "maxY": 99.4375}, "class_id": 0, "box_caption": "balloons 0.003", "scores": {"class_score": 0.0026111602783203125}, "domain": "pixel"}, {"position": {"minX": 29.0, "minY": 226.75, "maxX": 187.5, "maxY": 458.25}, "class_id": 0, "box_caption": "balloons 0.003", "scores": {"class_score": 0.0026111602783203125}, "domain": "pixel"}, {"position": {"minX": 429.25, "minY": 527.0, "maxX": 642.0, "maxY": 717.0}, "class_id": 0, "box_caption": "balloons 0.003", "scores": {"class_score": 0.0026111602783203125}, "domain": "pixel"}, {"position": {"minX": 322.0, "minY": 37.875, "maxX": 570.5, "maxY": 310.5}, "class_id": 0, "box_caption": "balloons 0.003", "scores": {"class_score": 0.002590179443359375}, "domain": "pixel"}, {"position": {"minX": 590.0, "minY": 443.5, "maxX": 710.0, "maxY": 669.5}, "class_id": 0, "box_caption": "balloons 0.003", "scores": {"class_score": 0.0025806427001953125}, "domain": "pixel"}, {"position": {"minX": 234.75, "minY": 550.0, "maxX": 623.0, "maxY": 776.0}, "class_id": 0, "box_caption": "balloons 0.003", "scores": {"class_score": 0.0025615692138671875}, "domain": "pixel"}, {"position": {"minX": 633.5, "minY": 235.5, "maxX": 703.5, "maxY": 480.5}, "class_id": 0, "box_caption": "balloons 0.003", "scores": {"class_score": 0.0025310516357421875}, "domain": "pixel"}, {"position": {"minX": 579.5, "minY": 597.0, "maxX": 666.5, "maxY": 714.0}, "class_id": 0, "box_caption": "balloons 0.003", "scores": {"class_score": 0.0025310516357421875}, "domain": "pixel"}, {"position": {"minX": 36.1875, "minY": 533.0, "maxX": 160.0, "maxY": 713.0}, "class_id": 0, "box_caption": "balloons 0.003", "scores": {"class_score": 0.002521514892578125}, "domain": "pixel"}, {"position": {"minX": 558.5, "minY": -77.25, "maxX": 765.5, "maxY": 129.25}, "class_id": 0, "box_caption": "balloons 0.003", "scores": {"class_score": 0.00250244140625}, "domain": "pixel"}, {"position": {"minX": 599.5, "minY": 513.5, "maxX": 716.5, "maxY": 678.5}, "class_id": 0, "box_caption": "balloons 0.002", "scores": {"class_score": 0.0024929046630859375}, "domain": "pixel"}, {"position": {"minX": 17.625, "minY": -8.8125, "maxX": 437.0, "maxY": 206.5}, "class_id": 0, "box_caption": "balloons 0.002", "scores": {"class_score": 0.0024929046630859375}, "domain": "pixel"}, {"position": {"minX": 577.0, "minY": 484.5, "maxX": 715.0, "maxY": 784.5}, "class_id": 0, "box_caption": "balloons 0.002", "scores": {"class_score": 0.0024929046630859375}, "domain": "pixel"}, {"position": {"minX": -34.65625, "minY": 566.5, "maxX": 46.71875, "maxY": 677.5}, "class_id": 0, "box_caption": "balloons 0.002", "scores": {"class_score": 0.0024814605712890625}, "domain": "pixel"}, {"position": {"minX": 440.0, "minY": 246.25, "maxX": 634.0, "maxY": 626.0}, "class_id": 0, "box_caption": "balloons 0.002", "scores": {"class_score": 0.0024814605712890625}, "domain": "pixel"}, {"position": {"minX": 242.5, "minY": 475.25, "maxX": 494.5, "maxY": 693.5}, "class_id": 0, "box_caption": "balloons 0.002", "scores": {"class_score": 0.002471923828125}, "domain": "pixel"}, {"position": {"minX": 634.0, "minY": 59.5, "maxX": 698.0, "maxY": 306.75}, "class_id": 0, "box_caption": "balloons 0.002", "scores": {"class_score": 0.0024623870849609375}, "domain": "pixel"}, {"position": {"minX": 406.5, "minY": 585.5, "maxX": 690.5, "maxY": 686.5}, "class_id": 0, "box_caption": "balloons 0.002", "scores": {"class_score": 0.00243377685546875}, "domain": "pixel"}, {"position": {"minX": 586.5, "minY": 628.0, "maxX": 667.5, "maxY": 658.0}, "class_id": 0, "box_caption": "balloons 0.002", "scores": {"class_score": 0.0023975372314453125}, "domain": "pixel"}, {"position": {"minX": 5.8125, "minY": -0.4375, "maxX": 155.0, "maxY": 163.75}, "class_id": 0, "box_caption": "balloons 0.002", "scores": {"class_score": 0.0023975372314453125}, "domain": "pixel"}, {"position": {"minX": 15.9375, "minY": 470.0, "maxX": 80.25, "maxY": 542.0}, "class_id": 0, "box_caption": "balloons 0.002", "scores": {"class_score": 0.0023784637451171875}, "domain": "pixel"}, {"position": {"minX": 596.5, "minY": 631.0, "maxX": 717.5, "maxY": 651.0}, "class_id": 0, "box_caption": "balloons 0.002", "scores": {"class_score": 0.0023784637451171875}, "domain": "pixel"}, {"position": {"minX": 562.0, "minY": 20.9375, "maxX": 636.0, "maxY": 72.0}, "class_id": 0, "box_caption": "balloons 0.002", "scores": {"class_score": 0.002349853515625}, "domain": "pixel"}, {"position": {"minX": 289.75, "minY": 370.75, "maxX": 636.0, "maxY": 623.0}, "class_id": 0, "box_caption": "balloons 0.002", "scores": {"class_score": 0.0023326873779296875}, "domain": "pixel"}, {"position": {"minX": 604.0, "minY": 561.5, "maxX": 668.0, "maxY": 653.5}, "class_id": 0, "box_caption": "balloons 0.002", "scores": {"class_score": 0.002323150634765625}, "domain": "pixel"}, {"position": {"minX": -14.0, "minY": 58.625, "maxX": 55.6875, "maxY": 299.0}, "class_id": 0, "box_caption": "balloons 0.002", "scores": {"class_score": 0.0023136138916015625}, "domain": "pixel"}, {"position": {"minX": 581.5, "minY": -49.8125, "maxX": 728.5, "maxY": 207.0}, "class_id": 0, "box_caption": "balloons 0.002", "scores": {"class_score": 0.0023059844970703125}, "domain": "pixel"}, {"position": {"minX": 307.5, "minY": -6.25, "maxX": 620.0, "maxY": 118.8125}, "class_id": 0, "box_caption": "balloons 0.002", "scores": {"class_score": 0.00229644775390625}, "domain": "pixel"}, {"position": {"minX": 543.0, "minY": 44.0, "maxX": 656.0, "maxY": 300.75}, "class_id": 0, "box_caption": "balloons 0.002", "scores": {"class_score": 0.00229644775390625}, "domain": "pixel"}, {"position": {"minX": 114.75, "minY": 12.625, "maxX": 451.75, "maxY": 454.5}, "class_id": 0, "box_caption": "balloons 0.002", "scores": {"class_score": 0.00229644775390625}, "domain": "pixel"}, {"position": {"minX": 586.5, "minY": 21.03125, "maxX": 642.5, "maxY": 74.75}, "class_id": 0, "box_caption": "balloons 0.002", "scores": {"class_score": 0.0022869110107421875}, "domain": "pixel"}, {"position": {"minX": 64.3125, "minY": 591.0, "maxX": 150.25, "maxY": 692.0}, "class_id": 0, "box_caption": "balloons 0.002", "scores": {"class_score": 0.0022869110107421875}, "domain": "pixel"}, {"position": {"minX": -53.8125, "minY": 605.0, "maxX": 85.3125, "maxY": 700.0}, "class_id": 0, "box_caption": "balloons 0.002", "scores": {"class_score": 0.002269744873046875}, "domain": "pixel"}, {"position": {"minX": -79.0, "minY": -53.8125, "maxX": 120.875, "maxY": 217.75}, "class_id": 0, "box_caption": "balloons 0.002", "scores": {"class_score": 0.002269744873046875}, "domain": "pixel"}, {"position": {"minX": 386.75, "minY": 489.5, "maxX": 544.0, "maxY": 783.5}, "class_id": 0, "box_caption": "balloons 0.002", "scores": {"class_score": 0.0022602081298828125}, "domain": "pixel"}, {"position": {"minX": 171.375, "minY": 8.0625, "maxX": 518.0, "maxY": 139.0}, "class_id": 0, "box_caption": "balloons 0.002", "scores": {"class_score": 0.0022525787353515625}, "domain": "pixel"}, {"position": {"minX": 458.0, "minY": 332.0, "maxX": 648.0, "maxY": 670.5}, "class_id": 0, "box_caption": "balloons 0.002", "scores": {"class_score": 0.0022335052490234375}, "domain": "pixel"}, {"position": {"minX": 467.0, "minY": 608.0, "maxX": 523.0, "maxY": 678.0}, "class_id": 0, "box_caption": "balloons 0.002", "scores": {"class_score": 0.0022258758544921875}, "domain": "pixel"}, {"position": {"minX": -18.5625, "minY": 329.25, "maxX": 54.25, "maxY": 611.0}, "class_id": 0, "box_caption": "balloons 0.002", "scores": {"class_score": 0.002216339111328125}, "domain": "pixel"}, {"position": {"minX": 119.25, "minY": 257.0, "maxX": 296.25, "maxY": 478.0}, "class_id": 0, "box_caption": "balloons 0.002", "scores": {"class_score": 0.002208709716796875}, "domain": "pixel"}, {"position": {"minX": 211.125, "minY": 377.25, "maxX": 585.0, "maxY": 811.0}, "class_id": 0, "box_caption": "balloons 0.002", "scores": {"class_score": 0.002208709716796875}, "domain": "pixel"}, {"position": {"minX": 454.25, "minY": 453.25, "maxX": 681.0, "maxY": 729.0}, "class_id": 0, "box_caption": "balloons 0.002", "scores": {"class_score": 0.0021991729736328125}, "domain": "pixel"}, {"position": {"minX": 544.0, "minY": 568.5, "maxX": 631.0, "maxY": 678.5}, "class_id": 0, "box_caption": "balloons 0.002", "scores": {"class_score": 0.0021915435791015625}, "domain": "pixel"}, {"position": {"minX": 24.5, "minY": 4.0, "maxX": 206.75, "maxY": 232.25}, "class_id": 0, "box_caption": "balloons 0.002", "scores": {"class_score": 0.0021648406982421875}, "domain": "pixel"}, {"position": {"minX": 491.0, "minY": 589.0, "maxX": 554.0, "maxY": 657.0}, "class_id": 0, "box_caption": "balloons 0.002", "scores": {"class_score": 0.0021572113037109375}, "domain": "pixel"}, {"position": {"minX": 495.0, "minY": -39.0625, "maxX": 697.0, "maxY": 83.875}, "class_id": 0, "box_caption": "balloons 0.002", "scores": {"class_score": 0.0021572113037109375}, "domain": "pixel"}, {"position": {"minX": 13.375, "minY": 24.03125, "maxX": 105.75, "maxY": 97.5}, "class_id": 0, "box_caption": "balloons 0.002", "scores": {"class_score": 0.002140045166015625}, "domain": "pixel"}, {"position": {"minX": -39.5, "minY": -6.125, "maxX": 204.0, "maxY": 93.25}, "class_id": 0, "box_caption": "balloons 0.002", "scores": {"class_score": 0.002140045166015625}, "domain": "pixel"}, {"position": {"minX": 517.5, "minY": 26.421875, "maxX": 651.5, "maxY": 64.0}, "class_id": 0, "box_caption": "balloons 0.002", "scores": {"class_score": 0.002132415771484375}, "domain": "pixel"}, {"position": {"minX": 16.5, "minY": 231.0, "maxX": 165.25, "maxY": 611.5}, "class_id": 0, "box_caption": "balloons 0.002", "scores": {"class_score": 0.002124786376953125}, "domain": "pixel"}, {"position": {"minX": 68.375, "minY": 30.6875, "maxX": 180.0, "maxY": 63.8125}, "class_id": 0, "box_caption": "balloons 0.002", "scores": {"class_score": 0.0021076202392578125}, "domain": "pixel"}, {"position": {"minX": 571.0, "minY": 641.5, "maxX": 679.0, "maxY": 671.5}, "class_id": 0, "box_caption": "balloons 0.002", "scores": {"class_score": 0.0021076202392578125}, "domain": "pixel"}, {"position": {"minX": 69.1875, "minY": 545.0, "maxX": 190.25, "maxY": 761.0}, "class_id": 0, "box_caption": "balloons 0.002", "scores": {"class_score": 0.0021076202392578125}, "domain": "pixel"}, {"position": {"minX": 130.25, "minY": 268.0, "maxX": 593.0, "maxY": 723.0}, "class_id": 0, "box_caption": "balloons 0.002", "scores": {"class_score": 0.0020999908447265625}, "domain": "pixel"}, {"position": {"minX": 544.5, "minY": 193.5, "maxX": 640.5, "maxY": 424.0}, "class_id": 0, "box_caption": "balloons 0.002", "scores": {"class_score": 0.00208282470703125}, "domain": "pixel"}, {"position": {"minX": 457.0, "minY": 59.375, "maxX": 474.0, "maxY": 120.625}, "class_id": 0, "box_caption": "balloons 0.002", "scores": {"class_score": 0.0020751953125}, "domain": "pixel"}, {"position": {"minX": 27.5625, "minY": 38.875, "maxX": 185.75, "maxY": 321.5}, "class_id": 0, "box_caption": "balloons 0.002", "scores": {"class_score": 0.0020751953125}, "domain": "pixel"}, {"position": {"minX": -11.875, "minY": 40.875, "maxX": 493.5, "maxY": 525.0}, "class_id": 0, "box_caption": "balloons 0.002", "scores": {"class_score": 0.0020751953125}, "domain": "pixel"}, {"position": {"minX": 563.0, "minY": -13.0, "maxX": 637.0, "maxY": 65.3125}, "class_id": 0, "box_caption": "balloons 0.002", "scores": {"class_score": 0.0020580291748046875}, "domain": "pixel"}, {"position": {"minX": 8.53125, "minY": 475.5, "maxX": 58.21875, "maxY": 577.5}, "class_id": 0, "box_caption": "balloons 0.002", "scores": {"class_score": 0.0020275115966796875}, "domain": "pixel"}, {"position": {"minX": 17.78125, "minY": 17.96875, "maxX": 129.125, "maxY": 79.125}, "class_id": 0, "box_caption": "balloons 0.002", "scores": {"class_score": 0.0020198822021484375}, "domain": "pixel"}, {"position": {"minX": 24.75, "minY": 98.75, "maxX": 102.25, "maxY": 152.25}, "class_id": 0, "box_caption": "balloons 0.002", "scores": {"class_score": 0.0020198822021484375}, "domain": "pixel"}, {"position": {"minX": -57.34375, "minY": 324.0, "maxX": 92.875, "maxY": 670.0}, "class_id": 0, "box_caption": "balloons 0.002", "scores": {"class_score": 0.0020198822021484375}, "domain": "pixel"}, {"position": {"minX": 16.0, "minY": 15.3125, "maxX": 104.25, "maxY": 51.1875}, "class_id": 0, "box_caption": "balloons 0.002", "scores": {"class_score": 0.002010345458984375}, "domain": "pixel"}, {"position": {"minX": 16.375, "minY": 199.25, "maxX": 146.125, "maxY": 424.25}, "class_id": 0, "box_caption": "balloons 0.002", "scores": {"class_score": 0.002002716064453125}, "domain": "pixel"}, {"position": {"minX": 83.125, "minY": 228.0, "maxX": 266.5, "maxY": 452.0}, "class_id": 0, "box_caption": "balloons 0.002", "scores": {"class_score": 0.002002716064453125}, "domain": "pixel"}, {"position": {"minX": 117.875, "minY": 34.9375, "maxX": 256.0, "maxY": 60.0}, "class_id": 0, "box_caption": "balloons 0.002", "scores": {"class_score": 0.001987457275390625}, "domain": "pixel"}, {"position": {"minX": 189.0, "minY": -7.75, "maxX": 504.0, "maxY": 218.875}, "class_id": 0, "box_caption": "balloons 0.002", "scores": {"class_score": 0.001987457275390625}, "domain": "pixel"}, {"position": {"minX": 123.75, "minY": 32.21875, "maxX": 484.25, "maxY": 69.125}, "class_id": 0, "box_caption": "balloons 0.002", "scores": {"class_score": 0.001979827880859375}, "domain": "pixel"}, {"position": {"minX": 68.8125, "minY": 36.125, "maxX": 218.5, "maxY": 384.0}, "class_id": 0, "box_caption": "balloons 0.002", "scores": {"class_score": 0.001979827880859375}, "domain": "pixel"}, {"position": {"minX": 602.5, "minY": 592.0, "maxX": 706.5, "maxY": 659.0}, "class_id": 0, "box_caption": "balloons 0.002", "scores": {"class_score": 0.001972198486328125}, "domain": "pixel"}, {"position": {"minX": 5.375, "minY": 21.625, "maxX": 402.5, "maxY": 387.5}, "class_id": 0, "box_caption": "balloons 0.002", "scores": {"class_score": 0.001972198486328125}, "domain": "pixel"}, {"position": {"minX": 63.0, "minY": 617.5, "maxX": 104.5, "maxY": 636.5}, "class_id": 0, "box_caption": "balloons 0.002", "scores": {"class_score": 0.001964569091796875}, "domain": "pixel"}, {"position": {"minX": -81.625, "minY": 2.25, "maxX": 120.0, "maxY": 529.0}, "class_id": 0, "box_caption": "balloons 0.002", "scores": {"class_score": 0.001956939697265625}, "domain": "pixel"}, {"position": {"minX": 350.0, "minY": 3.9375, "maxX": 367.5, "maxY": 159.0}, "class_id": 0, "box_caption": "balloons 0.002", "scores": {"class_score": 0.001934051513671875}, "domain": "pixel"}, {"position": {"minX": 172.125, "minY": 623.5, "maxX": 444.0, "maxY": 691.5}, "class_id": 0, "box_caption": "balloons 0.002", "scores": {"class_score": 0.001934051513671875}, "domain": "pixel"}, {"position": {"minX": 27.921875, "minY": 246.625, "maxX": 45.4375, "maxY": 267.5}, "class_id": 0, "box_caption": "balloons 0.002", "scores": {"class_score": 0.0019121170043945312}, "domain": "pixel"}, {"position": {"minX": 167.25, "minY": 624.0, "maxX": 270.0, "maxY": 685.0}, "class_id": 0, "box_caption": "balloons 0.002", "scores": {"class_score": 0.0019121170043945312}, "domain": "pixel"}, {"position": {"minX": 64.75, "minY": 190.75, "maxX": 170.875, "maxY": 292.25}, "class_id": 0, "box_caption": "balloons 0.002", "scores": {"class_score": 0.0019121170043945312}, "domain": "pixel"}, {"position": {"minX": -46.5, "minY": -51.4375, "maxX": 408.5, "maxY": 145.25}, "class_id": 0, "box_caption": "balloons 0.002", "scores": {"class_score": 0.0019121170043945312}, "domain": "pixel"}, {"position": {"minX": 139.0, "minY": 228.5, "maxX": 345.75, "maxY": 447.5}, "class_id": 0, "box_caption": "balloons 0.002", "scores": {"class_score": 0.0018968582153320312}, "domain": "pixel"}, {"position": {"minX": 65.4375, "minY": 327.75, "maxX": 229.0, "maxY": 606.0}, "class_id": 0, "box_caption": "balloons 0.002", "scores": {"class_score": 0.0018968582153320312}, "domain": "pixel"}, {"position": {"minX": 558.5, "minY": 91.25, "maxX": 772.5, "maxY": 590.0}, "class_id": 0, "box_caption": "balloons 0.002", "scores": {"class_score": 0.0018968582153320312}, "domain": "pixel"}, {"position": {"minX": -36.40625, "minY": -10.375, "maxX": 81.0, "maxY": 165.875}, "class_id": 0, "box_caption": "balloons 0.002", "scores": {"class_score": 0.0018892288208007812}, "domain": "pixel"}, {"position": {"minX": 69.0, "minY": 454.75, "maxX": 281.5, "maxY": 670.5}, "class_id": 0, "box_caption": "balloons 0.002", "scores": {"class_score": 0.0018892288208007812}, "domain": "pixel"}, {"position": {"minX": 92.875, "minY": 360.25, "maxX": 265.0, "maxY": 630.0}, "class_id": 0, "box_caption": "balloons 0.002", "scores": {"class_score": 0.0018672943115234375}, "domain": "pixel"}, {"position": {"minX": -41.25, "minY": 330.75, "maxX": 189.75, "maxY": 656.0}, "class_id": 0, "box_caption": "balloons 0.002", "scores": {"class_score": 0.0018672943115234375}, "domain": "pixel"}, {"position": {"minX": 638.0, "minY": 213.25, "maxX": 697.0, "maxY": 403.25}, "class_id": 0, "box_caption": "balloons 0.002", "scores": {"class_score": 0.0018606185913085938}, "domain": "pixel"}, {"position": {"minX": 12.5, "minY": 4.0, "maxX": 287.25, "maxY": 96.125}, "class_id": 0, "box_caption": "balloons 0.002", "scores": {"class_score": 0.0018529891967773438}, "domain": "pixel"}, {"position": {"minX": 444.5, "minY": 177.25, "maxX": 729.5, "maxY": 625.0}, "class_id": 0, "box_caption": "balloons 0.002", "scores": {"class_score": 0.0018463134765625}, "domain": "pixel"}, {"position": {"minX": 111.4375, "minY": 200.0, "maxX": 195.0, "maxY": 277.25}, "class_id": 0, "box_caption": "balloons 0.002", "scores": {"class_score": 0.00183868408203125}, "domain": "pixel"}, {"position": {"minX": -43.75, "minY": 600.0, "maxX": 129.625, "maxY": 660.0}, "class_id": 0, "box_caption": "balloons 0.002", "scores": {"class_score": 0.00183868408203125}, "domain": "pixel"}, {"position": {"minX": -109.75, "minY": 447.75, "maxX": 283.25, "maxY": 660.0}, "class_id": 0, "box_caption": "balloons 0.002", "scores": {"class_score": 0.00183868408203125}, "domain": "pixel"}, {"position": {"minX": 62.5, "minY": 439.75, "maxX": 407.0, "maxY": 747.0}, "class_id": 0, "box_caption": "balloons 0.002", "scores": {"class_score": 0.0018310546875}, "domain": "pixel"}, {"position": {"minX": 28.90625, "minY": -13.171875, "maxX": 83.25, "maxY": 50.5625}, "class_id": 0, "box_caption": "balloons 0.002", "scores": {"class_score": 0.0018243789672851562}, "domain": "pixel"}, {"position": {"minX": 621.0, "minY": 0.0, "maxX": 715.0, "maxY": 269.75}, "class_id": 0, "box_caption": "balloons 0.002", "scores": {"class_score": 0.0018243789672851562}, "domain": "pixel"}, {"position": {"minX": 55.75, "minY": 118.5, "maxX": 503.75, "maxY": 670.5}, "class_id": 0, "box_caption": "balloons 0.002", "scores": {"class_score": 0.0018243789672851562}, "domain": "pixel"}, {"position": {"minX": 310.5, "minY": 229.75, "maxX": 406.0, "maxY": 309.75}, "class_id": 0, "box_caption": "balloons 0.002", "scores": {"class_score": 0.0018177032470703125}, "domain": "pixel"}, {"position": {"minX": 37.875, "minY": 305.0, "maxX": 298.5, "maxY": 682.0}, "class_id": 0, "box_caption": "balloons 0.002", "scores": {"class_score": 0.0018177032470703125}, "domain": "pixel"}, {"position": {"minX": 59.3125, "minY": 572.5, "maxX": 117.0625, "maxY": 680.5}, "class_id": 0, "box_caption": "balloons 0.002", "scores": {"class_score": 0.0018100738525390625}, "domain": "pixel"}, {"position": {"minX": 15.25, "minY": 47.25, "maxX": 152.125, "maxY": 242.75}, "class_id": 0, "box_caption": "balloons 0.002", "scores": {"class_score": 0.0018100738525390625}, "domain": "pixel"}, {"position": {"minX": 80.4375, "minY": 141.625, "maxX": 200.0, "maxY": 301.5}, "class_id": 0, "box_caption": "balloons 0.002", "scores": {"class_score": 0.0018100738525390625}, "domain": "pixel"}, {"position": {"minX": 545.0, "minY": -108.0, "maxX": 761.0, "maxY": 244.75}, "class_id": 0, "box_caption": "balloons 0.002", "scores": {"class_score": 0.0018100738525390625}, "domain": "pixel"}, {"position": {"minX": 354.0, "minY": -1.0, "maxX": 631.0, "maxY": 475.5}, "class_id": 0, "box_caption": "balloons 0.002", "scores": {"class_score": 0.0018100738525390625}, "domain": "pixel"}, {"position": {"minX": 453.75, "minY": 88.4375, "maxX": 475.25, "maxY": 123.0625}, "class_id": 0, "box_caption": "balloons 0.002", "scores": {"class_score": 0.0018033981323242188}, "domain": "pixel"}, {"position": {"minX": 100.8125, "minY": 24.296875, "maxX": 209.25, "maxY": 71.125}, "class_id": 0, "box_caption": "balloons 0.002", "scores": {"class_score": 0.0018033981323242188}, "domain": "pixel"}, {"position": {"minX": 593.0, "minY": 3.875, "maxX": 702.0, "maxY": 53.65625}, "class_id": 0, "box_caption": "balloons 0.002", "scores": {"class_score": 0.0017957687377929688}, "domain": "pixel"}, {"position": {"minX": 209.875, "minY": 283.75, "maxX": 323.5, "maxY": 383.25}, "class_id": 0, "box_caption": "balloons 0.002", "scores": {"class_score": 0.0017957687377929688}, "domain": "pixel"}, {"position": {"minX": 510.0, "minY": 236.875, "maxX": 652.0, "maxY": 604.0}, "class_id": 0, "box_caption": "balloons 0.002", "scores": {"class_score": 0.0017957687377929688}, "domain": "pixel"}, {"position": {"minX": -37.28125, "minY": 488.5, "maxX": 136.125, "maxY": 634.5}, "class_id": 0, "box_caption": "balloons 0.002", "scores": {"class_score": 0.0017957687377929688}, "domain": "pixel"}, {"position": {"minX": 117.1875, "minY": 47.4375, "maxX": 307.25, "maxY": 84.5625}, "class_id": 0, "box_caption": "balloons 0.002", "scores": {"class_score": 0.0017824172973632812}, "domain": "pixel"}, {"position": {"minX": -43.625, "minY": 36.125, "maxX": 86.0, "maxY": 388.0}, "class_id": 0, "box_caption": "balloons 0.002", "scores": {"class_score": 0.0017824172973632812}, "domain": "pixel"}, {"position": {"minX": 5.34375, "minY": 205.125, "maxX": 83.875, "maxY": 418.0}, "class_id": 0, "box_caption": "balloons 0.002", "scores": {"class_score": 0.0017747879028320312}, "domain": "pixel"}, {"position": {"minX": 297.75, "minY": 225.75, "maxX": 421.25, "maxY": 282.0}, "class_id": 0, "box_caption": "balloons 0.002", "scores": {"class_score": 0.0017681121826171875}, "domain": "pixel"}, {"position": {"minX": 612.5, "minY": 536.5, "maxX": 663.5, "maxY": 641.5}, "class_id": 0, "box_caption": "balloons 0.002", "scores": {"class_score": 0.0017681121826171875}, "domain": "pixel"}, {"position": {"minX": 95.625, "minY": 42.40625, "maxX": 459.5, "maxY": 158.875}, "class_id": 0, "box_caption": "balloons 0.002", "scores": {"class_score": 0.0017681121826171875}, "domain": "pixel"}, {"position": {"minX": 29.125, "minY": 238.25, "maxX": 45.875, "maxY": 258.75}, "class_id": 0, "box_caption": "balloons 0.002", "scores": {"class_score": 0.0017547607421875}, "domain": "pixel"}, {"position": {"minX": -12.53125, "minY": 269.25, "maxX": 85.125, "maxY": 360.25}, "class_id": 0, "box_caption": "balloons 0.002", "scores": {"class_score": 0.0017547607421875}, "domain": "pixel"}, {"position": {"minX": 33.125, "minY": 18.8125, "maxX": 215.375, "maxY": 160.75}, "class_id": 0, "box_caption": "balloons 0.002", "scores": {"class_score": 0.0017547607421875}, "domain": "pixel"}, {"position": {"minX": 140.75, "minY": -4.71875, "maxX": 250.75, "maxY": 70.75}, "class_id": 0, "box_caption": "balloons 0.002", "scores": {"class_score": 0.0017337799072265625}, "domain": "pixel"}, {"position": {"minX": 590.0, "minY": 575.5, "maxX": 649.0, "maxY": 639.5}, "class_id": 0, "box_caption": "balloons 0.002", "scores": {"class_score": 0.0017337799072265625}, "domain": "pixel"}, {"position": {"minX": 566.5, "minY": 582.5, "maxX": 641.5, "maxY": 667.5}, "class_id": 0, "box_caption": "balloons 0.002", "scores": {"class_score": 0.0017337799072265625}, "domain": "pixel"}, {"position": {"minX": 361.5, "minY": 26.90625, "maxX": 386.0, "maxY": 131.25}, "class_id": 0, "box_caption": "balloons 0.002", "scores": {"class_score": 0.0017271041870117188}, "domain": "pixel"}, {"position": {"minX": 310.0, "minY": 22.875, "maxX": 515.0, "maxY": 264.5}, "class_id": 0, "box_caption": "balloons 0.002", "scores": {"class_score": 0.0017271041870117188}, "domain": "pixel"}, {"position": {"minX": 2.5625, "minY": 93.625, "maxX": 89.5625, "maxY": 128.125}, "class_id": 0, "box_caption": "balloons 0.002", "scores": {"class_score": 0.001720428466796875}, "domain": "pixel"}, {"position": {"minX": 597.0, "minY": 596.0, "maxX": 646.0, "maxY": 656.0}, "class_id": 0, "box_caption": "balloons 0.002", "scores": {"class_score": 0.0017137527465820312}, "domain": "pixel"}, {"position": {"minX": 639.5, "minY": 127.8125, "maxX": 694.5, "maxY": 364.5}, "class_id": 0, "box_caption": "balloons 0.002", "scores": {"class_score": 0.0017137527465820312}, "domain": "pixel"}, {"position": {"minX": 143.0, "minY": 28.9375, "maxX": 418.5, "maxY": 257.25}, "class_id": 0, "box_caption": "balloons 0.002", "scores": {"class_score": 0.0017137527465820312}, "domain": "pixel"}, {"position": {"minX": -51.3125, "minY": 81.625, "maxX": 296.0, "maxY": 387.5}, "class_id": 0, "box_caption": "balloons 0.002", "scores": {"class_score": 0.0017137527465820312}, "domain": "pixel"}, {"position": {"minX": 75.3125, "minY": 45.625, "maxX": 172.25, "maxY": 74.375}, "class_id": 0, "box_caption": "balloons 0.002", "scores": {"class_score": 0.0017070770263671875}, "domain": "pixel"}, {"position": {"minX": 16.890625, "minY": 525.0, "maxX": 40.375, "maxY": 580.0}, "class_id": 0, "box_caption": "balloons 0.002", "scores": {"class_score": 0.0017070770263671875}, "domain": "pixel"}, {"position": {"minX": 279.25, "minY": 526.0, "maxX": 485.75, "maxY": 750.0}, "class_id": 0, "box_caption": "balloons 0.002", "scores": {"class_score": 0.0017070770263671875}, "domain": "pixel"}, {"position": {"minX": 391.75, "minY": 17.5625, "maxX": 609.0, "maxY": 258.5}, "class_id": 0, "box_caption": "balloons 0.002", "scores": {"class_score": 0.0017070770263671875}, "domain": "pixel"}, {"position": {"minX": 548.5, "minY": 251.875, "maxX": 633.5, "maxY": 494.0}, "class_id": 0, "box_caption": "balloons 0.002", "scores": {"class_score": 0.0017070770263671875}, "domain": "pixel"}, {"position": {"minX": -5.28125, "minY": 396.0, "maxX": 110.75, "maxY": 616.5}, "class_id": 0, "box_caption": "balloons 0.002", "scores": {"class_score": 0.0017070770263671875}, "domain": "pixel"}, {"position": {"minX": 4.015625, "minY": 455.5, "maxX": 32.8125, "maxY": 597.5}, "class_id": 0, "box_caption": "balloons 0.002", "scores": {"class_score": 0.0017004013061523438}, "domain": "pixel"}, {"position": {"minX": 77.5, "minY": 187.5, "maxX": 197.25, "maxY": 218.5}, "class_id": 0, "box_caption": "balloons 0.002", "scores": {"class_score": 0.0017004013061523438}, "domain": "pixel"}, {"position": {"minX": 378.5, "minY": 357.0, "maxX": 555.0, "maxY": 627.5}, "class_id": 0, "box_caption": "balloons 0.002", "scores": {"class_score": 0.0017004013061523438}, "domain": "pixel"}, {"position": {"minX": 141.75, "minY": 4.734375, "maxX": 218.5, "maxY": 63.25}, "class_id": 0, "box_caption": "balloons 0.002", "scores": {"class_score": 0.0016937255859375}, "domain": "pixel"}, {"position": {"minX": 101.375, "minY": 195.0, "maxX": 170.125, "maxY": 236.25}, "class_id": 0, "box_caption": "balloons 0.002", "scores": {"class_score": 0.0016870498657226562}, "domain": "pixel"}, {"position": {"minX": 588.5, "minY": 66.75, "maxX": 714.5, "maxY": 588.0}, "class_id": 0, "box_caption": "balloons 0.002", "scores": {"class_score": 0.0016870498657226562}, "domain": "pixel"}, {"position": {"minX": 218.0, "minY": 581.0, "maxX": 380.0, "maxY": 670.0}, "class_id": 0, "box_caption": "balloons 0.002", "scores": {"class_score": 0.0016813278198242188}, "domain": "pixel"}, {"position": {"minX": 460.5, "minY": 209.75, "maxX": 591.5, "maxY": 472.25}, "class_id": 0, "box_caption": "balloons 0.002", "scores": {"class_score": 0.0016613006591796875}, "domain": "pixel"}, {"position": {"minX": 19.8125, "minY": 81.1875, "maxX": 106.0625, "maxY": 141.5}, "class_id": 0, "box_caption": "balloons 0.002", "scores": {"class_score": 0.0016489028930664062}, "domain": "pixel"}, {"position": {"minX": -19.40625, "minY": 14.8125, "maxX": 70.125, "maxY": 206.0}, "class_id": 0, "box_caption": "balloons 0.002", "scores": {"class_score": 0.0016489028930664062}, "domain": "pixel"}, {"position": {"minX": 435.5, "minY": 81.875, "maxX": 460.5, "maxY": 137.125}, "class_id": 0, "box_caption": "balloons 0.002", "scores": {"class_score": 0.0016355514526367188}, "domain": "pixel"}, {"position": {"minX": -6.359375, "minY": 535.0, "maxX": 57.5625, "maxY": 631.0}, "class_id": 0, "box_caption": "balloons 0.002", "scores": {"class_score": 0.0016355514526367188}, "domain": "pixel"}, {"position": {"minX": 609.0, "minY": 645.5, "maxX": 676.0, "maxY": 665.5}, "class_id": 0, "box_caption": "balloons 0.002", "scores": {"class_score": 0.0016355514526367188}, "domain": "pixel"}, {"position": {"minX": 582.5, "minY": 87.375, "maxX": 674.5, "maxY": 331.5}, "class_id": 0, "box_caption": "balloons 0.002", "scores": {"class_score": 0.0016355514526367188}, "domain": "pixel"}, {"position": {"minX": 181.5, "minY": 318.0, "maxX": 437.0, "maxY": 530.5}, "class_id": 0, "box_caption": "balloons 0.002", "scores": {"class_score": 0.0016355514526367188}, "domain": "pixel"}, {"position": {"minX": 35.9375, "minY": 352.0, "maxX": 124.0625, "maxY": 589.5}, "class_id": 0, "box_caption": "balloons 0.002", "scores": {"class_score": 0.0016355514526367188}, "domain": "pixel"}, {"position": {"minX": -12.25, "minY": 16.4375, "maxX": 121.625, "maxY": 142.25}, "class_id": 0, "box_caption": "balloons 0.002", "scores": {"class_score": 0.001628875732421875}, "domain": "pixel"}, {"position": {"minX": 24.890625, "minY": 602.5, "maxX": 88.125, "maxY": 680.5}, "class_id": 0, "box_caption": "balloons 0.002", "scores": {"class_score": 0.0016231536865234375}, "domain": "pixel"}, {"position": {"minX": 19.78125, "minY": 462.0, "maxX": 108.5, "maxY": 550.0}, "class_id": 0, "box_caption": "balloons 0.002", "scores": {"class_score": 0.0016164779663085938}, "domain": "pixel"}, {"position": {"minX": 46.0, "minY": 569.0, "maxX": 101.0, "maxY": 681.0}, "class_id": 0, "box_caption": "balloons 0.002", "scores": {"class_score": 0.0016164779663085938}, "domain": "pixel"}, {"position": {"minX": 471.5, "minY": 610.0, "maxX": 546.5, "maxY": 640.0}, "class_id": 0, "box_caption": "balloons 0.002", "scores": {"class_score": 0.0016164779663085938}, "domain": "pixel"}, {"position": {"minX": 621.5, "minY": 607.5, "maxX": 659.5, "maxY": 644.5}, "class_id": 0, "box_caption": "balloons 0.002", "scores": {"class_score": 0.0016164779663085938}, "domain": "pixel"}, {"position": {"minX": 143.5, "minY": 489.0, "maxX": 340.25, "maxY": 696.0}, "class_id": 0, "box_caption": "balloons 0.002", "scores": {"class_score": 0.0016107559204101562}, "domain": "pixel"}, {"position": {"minX": 191.75, "minY": 500.5, "maxX": 427.25, "maxY": 676.5}, "class_id": 0, "box_caption": "balloons 0.002", "scores": {"class_score": 0.0016107559204101562}, "domain": "pixel"}, {"position": {"minX": 364.0, "minY": 294.5, "maxX": 611.0, "maxY": 696.5}, "class_id": 0, "box_caption": "balloons 0.002", "scores": {"class_score": 0.0016107559204101562}, "domain": "pixel"}, {"position": {"minX": 591.5, "minY": 183.25, "maxX": 664.5, "maxY": 432.25}, "class_id": 0, "box_caption": "balloons 0.002", "scores": {"class_score": 0.0016040802001953125}, "domain": "pixel"}, {"position": {"minX": 508.25, "minY": 4.703125, "maxX": 632.0, "maxY": 52.125}, "class_id": 0, "box_caption": "balloons 0.002", "scores": {"class_score": 0.0015974044799804688}, "domain": "pixel"}, {"position": {"minX": 226.0, "minY": 325.75, "maxX": 335.5, "maxY": 404.75}, "class_id": 0, "box_caption": "balloons 0.002", "scores": {"class_score": 0.0015974044799804688}, "domain": "pixel"}, {"position": {"minX": -4.34375, "minY": 74.4375, "maxX": 113.875, "maxY": 277.75}, "class_id": 0, "box_caption": "balloons 0.002", "scores": {"class_score": 0.0015974044799804688}, "domain": "pixel"}, {"position": {"minX": 25.75, "minY": 248.25, "maxX": 132.25, "maxY": 494.75}, "class_id": 0, "box_caption": "balloons 0.002", "scores": {"class_score": 0.0015974044799804688}, "domain": "pixel"}, {"position": {"minX": 186.0, "minY": -13.375, "maxX": 299.0, "maxY": 76.25}, "class_id": 0, "box_caption": "balloons 0.002", "scores": {"class_score": 0.0015916824340820312}, "domain": "pixel"}, {"position": {"minX": 198.75, "minY": 214.5, "maxX": 323.75, "maxY": 284.25}, "class_id": 0, "box_caption": "balloons 0.002", "scores": {"class_score": 0.0015916824340820312}, "domain": "pixel"}, {"position": {"minX": 34.90625, "minY": 194.0, "maxX": 142.5, "maxY": 300.5}, "class_id": 0, "box_caption": "balloons 0.002", "scores": {"class_score": 0.0015916824340820312}, "domain": "pixel"}, {"position": {"minX": 155.25, "minY": 285.75, "maxX": 339.25, "maxY": 512.5}, "class_id": 0, "box_caption": "balloons 0.002", "scores": {"class_score": 0.0015916824340820312}, "domain": "pixel"}, {"position": {"minX": 493.75, "minY": 573.0, "maxX": 582.5, "maxY": 671.0}, "class_id": 0, "box_caption": "balloons 0.002", "scores": {"class_score": 0.0015850067138671875}, "domain": "pixel"}, {"position": {"minX": 607.0, "minY": -13.5625, "maxX": 709.0, "maxY": 165.0}, "class_id": 0, "box_caption": "balloons 0.002", "scores": {"class_score": 0.0015850067138671875}, "domain": "pixel"}, {"position": {"minX": 40.5625, "minY": 526.0, "maxX": 240.75, "maxY": 670.0}, "class_id": 0, "box_caption": "balloons 0.002", "scores": {"class_score": 0.0015850067138671875}, "domain": "pixel"}, {"position": {"minX": 44.0625, "minY": 595.5, "maxX": 297.0, "maxY": 658.5}, "class_id": 0, "box_caption": "balloons 0.002", "scores": {"class_score": 0.0015850067138671875}, "domain": "pixel"}, {"position": {"minX": 222.5, "minY": 297.5, "maxX": 341.5, "maxY": 365.0}, "class_id": 0, "box_caption": "balloons 0.002", "scores": {"class_score": 0.00157928466796875}, "domain": "pixel"}, {"position": {"minX": 164.375, "minY": 249.875, "maxX": 383.0, "maxY": 480.0}, "class_id": 0, "box_caption": "balloons 0.002", "scores": {"class_score": 0.00157928466796875}, "domain": "pixel"}, {"position": {"minX": 282.5, "minY": -16.53125, "maxX": 426.0, "maxY": 78.75}, "class_id": 0, "box_caption": "balloons 0.002", "scores": {"class_score": 0.0015735626220703125}, "domain": "pixel"}, {"position": {"minX": 505.0, "minY": 34.125, "maxX": 663.0, "maxY": 85.625}, "class_id": 0, "box_caption": "balloons 0.002", "scores": {"class_score": 0.0015735626220703125}, "domain": "pixel"}, {"position": {"minX": 45.875, "minY": -103.125, "maxX": 441.0, "maxY": 132.5}, "class_id": 0, "box_caption": "balloons 0.002", "scores": {"class_score": 0.0015735626220703125}, "domain": "pixel"}, {"position": {"minX": 115.6875, "minY": 87.0625, "maxX": 312.0, "maxY": 335.5}, "class_id": 0, "box_caption": "balloons 0.002", "scores": {"class_score": 0.0015611648559570312}, "domain": "pixel"}, {"position": {"minX": 504.75, "minY": 192.25, "maxX": 615.5, "maxY": 425.75}, "class_id": 0, "box_caption": "balloons 0.002", "scores": {"class_score": 0.0015611648559570312}, "domain": "pixel"}, {"position": {"minX": 355.75, "minY": 422.0, "maxX": 522.5, "maxY": 646.0}, "class_id": 0, "box_caption": "balloons 0.002", "scores": {"class_score": 0.0015611648559570312}, "domain": "pixel"}, {"position": {"minX": 214.5, "minY": 22.375, "maxX": 350.5, "maxY": 102.8125}, "class_id": 0, "box_caption": "balloons 0.002", "scores": {"class_score": 0.0015544891357421875}, "domain": "pixel"}, {"position": {"minX": 191.25, "minY": 266.75, "maxX": 315.25, "maxY": 368.25}, "class_id": 0, "box_caption": "balloons 0.002", "scores": {"class_score": 0.0015544891357421875}, "domain": "pixel"}], "class_labels": {"0": "balloons"}}